MANIFEST.in
README.rst
setup.py
docs/HISTORY.txt
docs/INSTALL.txt
docs/LICENSE.GPL
docs/LICENSE.txt
rt/__init__.py
rt.vuvuzela.egg-info/PKG-INFO
rt.vuvuzela.egg-info/SOURCES.txt
rt.vuvuzela.egg-info/dependency_links.txt
rt.vuvuzela.egg-info/entry_points.txt
rt.vuvuzela.egg-info/namespace_packages.txt
rt.vuvuzela.egg-info/not-zip-safe
rt.vuvuzela.egg-info/requires.txt
rt.vuvuzela.egg-info/top_level.txt
rt/vuvuzela/README.txt
rt/vuvuzela/__init__.py
rt/vuvuzela/config.py
rt/vuvuzela/configure.zcml
rt/vuvuzela/browser/__init__.py
rt/vuvuzela/browser/configure.zcml
rt/vuvuzela/browser/vuvuzela.pt
rt/vuvuzela/browser/vuvuzela.py
rt/vuvuzela/interfaces/__init__.py
rt/vuvuzela/tests/__init__.py
rt/vuvuzela/tests/base.py
rt/vuvuzela/tests/test_doctest.py