Metadata-Version: 1.0
Name: rt.vuvuzela
Version: 1.0.1
Summary: Created while watching Italy on tv :)
Home-page: http://svn.plone.org/svn/collective/
Author: alert
Author-email: alessandro DOT pisa AT redturtle DOR net
License: GPL
Platform: UNKNOWN
Classifier: Framework :: Plone
Classifier: Intended Audience :: Developers
Classifier: License :: OSI Approved :: GNU General Public License (GPL)
